.coveragerc
.travis.yml
LICENSE
MANIFEST.in
README.rst
setup.py
jardb/__init__.py
jardb/autosave.py
jardb/compose.py
jardb/dblogging.py
jardb/errors.py
jardb/jardb.py
jardb/query.py
jardb/storage.py
jardb/util.py
jardb.egg-info/PKG-INFO
jardb.egg-info/SOURCES.txt
jardb.egg-info/dependency_links.txt
jardb.egg-info/top_level.txt
test/test-autosave.py
test/test-compose.py
test/test-errors.py
test/test-jardb.py
test/test-query.py
test/test-storage.py
test/test-util.py