Metadata-Version: 1.1
Name: jardb
Version: 0.0.5
Summary: A small Document Oriented Databse
Home-page: https://github.com/andytt/jardb
Author: Lutong Chen
Author-email: lutong98@mail.ustc.edu.cn
License: Copyright (c) 2018, Chen Lutong.
